{
  "request_id": "220713093149_e44871c7-cca8-5f9c-8dde-f5aabb7df54b",
  "status": "invalid",
  "request": {
    "source_credentials": "805202fb-0301-4776-bb0b-785c35aea043",
    "target_credentials": "60d9e676-2af9-4171-97f0-f68d94361653",
    "source_settings": {
      "$schema": "https://s.dev.y42.dev/integrations/mssql/0.0.0/source.json#sql_server"
    },
    "table_settings": {
      "$schema": "https://s.dev.y42.dev/integrations/mssql/0.0.0/table",
      "columns": [
        "Klasif3",
        "Cmb2",
        "Klasif2",
        "Klasif",
        "Bc",
        "Cmb",
        "Cmsh",
        "Dalje",
        "Njesi",
        "Marzhi",
        "Tatim",
        "Klasif4",
        "Tvsh",
        "Ditore",
        "Mini",
        "KostMes",
        "Pershkrim",
        "Javore",
        "Maks",
        "Kod",
        "Hyrje",
        "Mujore"
      ],
      "import": "BM15_dbo_vArtikuj"
    },
    "created_at": "2022-07-13T09:31:49.136780+00:00",
    "target": {
      "storage": {
        "type": "githubapp",
        "path": "/src/Integrations/RediSQLServer/vArtikuj",
        "id": "6:ff957504-4e37-4a27-8dd0-6a67bc8e8201",
        "branch": "main"
      },
      "info": {
        "app_id": "",
        "owner": "egi-gjevori",
        "repo": "y42_snowflake_s3_db",
        "commit_sha": "14d0b86cd88247386edd160dca2a3da1978c81f5"
      }
    },
    "context": {
      "company_id": 6,
      "company_slug": "y42-demo",
      "triggered_by_type": "user",
      "triggered_by_id": "81",
      "trial": true
    }
  },
  "created_at": "2022-07-13T09:31:49.136780+00:00",
  "failed_at": "2022-07-13T09:32:47.103041+00:00",
  "error_code": 500,
  "error_message": "import error",
  "_signature": "tm+DCGJfvGT/Nb1JNY9AYKjP2uNKYNwDpmPveRcs3qyfum4Ml/IqW34XSLCEq/hugtBMVjaASajCZf0fJOPXDg=="
}
