{
  "request_id": "220713102440_ecddf955-07f4-5375-9c8f-f2a81e3a5ef4",
  "status": "pending",
  "request": {
    "source_credentials": "805202fb-0301-4776-bb0b-785c35aea043",
    "target_credentials": "60d9e676-2af9-4171-97f0-f68d94361653",
    "source_settings": {
      "$schema": "https://s.dev.y42.dev/integrations/mssql/0.0.0/source.json#sql_server"
    },
    "table_settings": {
      "$schema": "https://s.dev.y42.dev/integrations/mssql/0.0.0/table",
      "columns": [
        "NRSERIAL",
        "FISSTATUS",
        "EXTEXP",
        "TAGRND",
        "FISLASTERRORTEXTEIC",
        "NRRENDDMG",
        "FISTVSHEFEKT",
        "VLTAX",
        "USI",
        "VLERTOT",
        "KLASIFIKIM1",
        "EXTIMPKOMENT",
        "FISKODOPERATOR",
        "NRDOK",
        "FISUUID",
        "NRDITARSHL",
        "LLOGTVSH",
        "SHENIM2",
        "NRDFTEXTRA",
        "FISXMLSTRING",
        "DTDOKDG",
        "POSTIM",
        "NRRENDORAMB",
        "NRRENDORFJT",
        "DTAF",
        "DATEDOK",
        "DATECREATE",
        "DTDMAG",
        "KTH",
        "VENHUAJ",
        "KURS1",
        "NRFISKALIZIM",
        "PAGESEARK",
        "KMON",
        "FISMENPAGESE",
        "FISIICSIG",
        "FISRESPONSEXMLEIC",
        "FISXMLSIGNED",
        "VLPATVSH",
        "PERQDS",
        "DTDSHOQ",
        "ISDOCFISCAL",
        "LETER",
        "NRDOKDG",
        "JOBCREATE",
        "FISEIC",
        "TAG",
        "NRRENDOROR",
        "SHENIM4",
        "MODPG",
        "LLOGZBR",
        "FISBUSINESSUNIT",
        "KODARK",
        "FISLASTERRORTEXTFIC",
        "NRFATST",
        "USM",
        "NRDMAG",
        "FISTIPDOK",
        "PARAPG",
        "FISRELATEDFIC",
        "SHENIM1",
        "TAGNR",
        "NRRENDORAR",
        "NRRENDORAQ",
        "DATEEDIT",
        "KMAG",
        "TAGLM",
        "KODFKL",
        "VLERZBR",
        "FISLASTERRORFIC",
        "EXTIMPID",
        "IMPORTTAG",
        "FISPDF",
        "LLOGARK",
        "KONFIRM",
        "KURS2",
        "FISRESPONSEXMLFIC",
        "EXTEXPKOMENT",
        "GRUP",
        "VLTVSH",
        "FRDMAG",
        "TROW",
        "FISDATEFUND",
        "FISDATEPARE",
        "FISFIC",
        "TIPDMG",
        "FISIIC",
        "FISQRCODELINK",
        "FISTCR",
        "FIRSTDOK",
        "KLASETVSH",
        "DTFATST",
        "LLOJDOK",
        "SHENIM3",
        "ISDG",
        "KODFISKAL",
        "KOD",
        "NRMAG",
        "SHENIME",
        "KODDG",
        "TIPFT",
        "NRFRAKS",
        "FISLASTERROREIC",
        "NRDFK",
        "FISKODREASON",
        "NIPT",
        "FISKALIZUAR",
        "NRDSHOQ",
        "KLASAKF",
        "NRDITAR",
        "PERQTVSH",
        "DATEARK",
        "PERQZBR",
        "RRETHI",
        "NRRENDOR",
        "FISPROCES",
        "DTDS",
        "KLASIFIKIM"
      ],
      "import": "BM15_dbo_FF"
    },
    "created_at": "2022-07-13T10:24:40.241269+00:00",
    "target": {
      "storage": {
        "type": "githubapp",
        "path": "/src/Integrations/RediSQLServer/FF",
        "id": "6:ff957504-4e37-4a27-8dd0-6a67bc8e8201",
        "branch": "main"
      },
      "info": {
        "app_id": "",
        "owner": "egi-gjevori",
        "repo": "y42_snowflake_s3_db",
        "commit_sha": "602c3a3ed45ad03f31b50bca22961a65fd4024d9"
      }
    },
    "context": {
      "company_id": 6,
      "company_slug": "y42-demo",
      "triggered_by_type": "user",
      "triggered_by_id": "81",
      "trial": true
    }
  },
  "created_at": "2022-07-13T10:24:40.241269+00:00",
  "_signature": "dKLKtz3mrqp5B1FN9AU4JYhfTiTuoDv4eN7JrYLnI0C4olmt8GGk+riOcJQiVYRpDO40WDnQu4Q9XesD/9eTDg=="
}
