{
  "request_id": "220713102424_d75e1f5a-c419-506c-8725-41f420d5ba83",
  "status": "pending",
  "request": {
    "source_credentials": "805202fb-0301-4776-bb0b-785c35aea043",
    "target_credentials": "60d9e676-2af9-4171-97f0-f68d94361653",
    "source_settings": {
      "$schema": "https://s.dev.y42.dev/integrations/mssql/0.0.0/source.json#sql_server"
    },
    "table_settings": {
      "$schema": "https://s.dev.y42.dev/integrations/mssql/0.0.0/table",
      "columns": [
        "ORDERNRAR",
        "LLOGTRANSP",
        "KALIMFJLMVAL",
        "PERQTATS",
        "IMPORTKODND",
        "LLOGMRRJET",
        "DATECEL",
        "ORDERNRBA",
        "USI",
        "ACTIVDTFK",
        "FREESKEMELM",
        "FALLOGGARANCIKL",
        "LLAUTARK",
        "AUTOPOSTLMFF",
        "AUTOPOSTLMFD",
        "LLOGXHMG",
        "AKTIVTRANSP",
        "LLOGDHURA",
        "LLOGTVSHMA",
        "ROWDIFFDEBIKREDI",
        "LLOGHUMBJE",
        "ARKEVLERELIMIT",
        "LLOGDHURB",
        "APLIKOKURSHIST",
        "AUTOPOSTLMFJ",
        "AUTOPOSTLMFH",
        "DUBLSCRANL",
        "ACTIVDTAR",
        "LLAUTBAN",
        "LLGVEPRIMAQ",
        "ACTIVDTVS",
        "KALIMARLMDEPLIST",
        "FUDEPLISTNGAREF",
        "LLOGTAX",
        "LLOGTVSHPG",
        "MODVEPRAUT",
        "LLGFURNITOR",
        "AUTOPOSTMGFJ",
        "KAUTARK",
        "ACTIVDTAQ",
        "NRDIGISERI",
        "TAG",
        "LLOGTATS",
        "LLOGZBR",
        "AUTOKRIJIMLM",
        "PERQTRANSP",
        "KALIMFHLMDEPLIST",
        "LLOGINV",
        "USM",
        "LLOGSH",
        "TAGNR",
        "LLOGDOG",
        "BLOKDOKARKEZERO",
        "KALIMABLM67DEPLIST",
        "AUTOPOSTLMDG",
        "AUTOPOSTLMVS",
        "AUTOPOSTLMAR",
        "ORDERNRAQ",
        "NDGJEND",
        "KALIMFFLMVAL",
        "KALIMFFLMDEPLIST",
        "LLOGARK",
        "HF_PERSH_RAP",
        "BLOKDOKBANKEZERO",
        "FAKALIMLMMG",
        "DEPLISTNGAART",
        "DUBLSCR",
        "AUTOPOSTMGFF",
        "LLOGDHURD",
        "LLOGAMBRJET",
        "KLDEPLISTNGAREF",
        "PROMOCFJSHOQ",
        "SERIAUTARK",
        "LLOGXHIRUES",
        "TROW",
        "LLGKLIENT",
        "ACTIVDTBA",
        "LISTEGRIDSHORTC",
        "LLOGDOKSH",
        "LMANALITIKFU",
        "LMANALITIKKL",
        "KAUTBAN",
        "LLOGPRMCFF",
        "HF_LLOG_RAP",
        "KALIMFJLMDEPLIST",
        "DUBLSCRBLK",
        "LLOGCEL",
        "DEPLISTNGASHERB",
        "ORDERNRFK",
        "KALIMFDLMDEPLIST",
        "LLOGPRMCFJ",
        "PERQTATB",
        "LLOGB",
        "LLOGFITIM",
        "LLOGBANK",
        "ORDERNRVS",
        "KALIMBALMDEPLIST",
        "FALLOGGARANCIART",
        "DEPLISTNGAAQKART",
        "PERQZBR",
        "LLOGTATB",
        "NRRENDOR",
        "AUTOPOSTLMAQ",
        "KALIMLMDSHOQFJ",
        "NRDOKAUTBANK",
        "LLOGDHURC",
        "AUTOPOSTLMBA"
      ],
      "import": "BM15_dbo_CONFIGLM"
    },
    "created_at": "2022-07-13T10:24:24.181458+00:00",
    "target": {
      "storage": {
        "type": "githubapp",
        "path": "/src/Integrations/RediSQLServer/CONFIGLM",
        "id": "6:ff957504-4e37-4a27-8dd0-6a67bc8e8201",
        "branch": "main"
      },
      "info": {
        "app_id": "",
        "owner": "egi-gjevori",
        "repo": "y42_snowflake_s3_db",
        "commit_sha": "91114c623a204b8daf72124511fe7fd95af457bb"
      }
    },
    "context": {
      "company_id": 6,
      "company_slug": "y42-demo",
      "triggered_by_type": "user",
      "triggered_by_id": "81",
      "trial": true
    }
  },
  "created_at": "2022-07-13T10:24:24.181458+00:00",
  "_signature": "FdaADpTD1ruzigTxEzbnjxg2QOUbdfgT/rzFenikH/dyCDNw5FmolCaU6SXTiNdCTRLKFOLLmjpdiQ7D7WqSBA=="
}
